arenacovid/__init__.py
arenacovid/models/__init__.py
arenacovid/models/curve_fitting.py
arenacovid/models/phase_space.py
arenacovid/models/sir.py
arenacovid-0.0.2.dist-info/DESCRIPTION.rst
arenacovid-0.0.2.dist-info/METADATA
arenacovid-0.0.2.dist-info/RECORD
arenacovid-0.0.2.dist-info/WHEEL
arenacovid-0.0.2.dist-info/metadata.json
arenacovid-0.0.2.dist-info/top_level.txt
