Metadata-Version: 2.0
Name: arenacovid
Version: 0.0.2
Summary: UNKNOWN
Home-page: UNKNOWN
Author: UNKNOWN
Author-email: UNKNOWN
License: UNKNOWN
Platform: UNKNOWN
Requires-Dist: pyarrow
Requires-Dist: pandas (==0.24.2)
Requires-Dist: s3fs (==0.2.2)
Requires-Dist: boto3
Requires-Dist: numba
Requires-Dist: pymc3
Requires-Dist: theano
Requires-Dist: matplotlib
